{"type": "article", "id": 6180, "title": "我们为什么膜蛤？ - 膜乎", "uid": 16, "topics": [10, 14, 617, 6642], "contents": "<b>由于沼气池已堵塞隐藏，为了方便广大膜友学习，不建议转沼气池。</b><br />\r\n<a href=\"url/img/aHR0cHM6Ly9pLmltZ3VyLmNvbS9tSm5ZWE1tLnBuZw\" title=\"https://i.imgur.com/mJnYXMm.png\" rel=\"nofollow noreferrer noopener\" target=\"_blank\"><img src=\"https://i.imgur.com/mJnYXMm.png\" alt=\"https://i.imgur.com/mJnYXMm.png\" style=\"max-width:100%\"></a> <br />\r\n记得在2011年的贴吧就有人用蛤蛤喝茶的头像。早年膜蛤的人都是反贼，李毅吧流行乳蛤段子，大多来自蛤三篇之一“怒斥记者”，也就在那时“图样图森破”等蛤语录开始流行。15/16年膜蛤盛行的时候，姿势水平低下的“尬膜小鬼”跟风膜蛤，他们不知道膜蛤梗在几年前就被玩烂了，这就是粉红蛤丝的由来。他们的观点通常是肯定共产党的大部分历史，认为就算党有一些不足也可以慢慢改进，在探索的过程中犯错可以接受。<br />\r\n前几年蛤丝们的共识是：<b>蛤丝一律不得膜包！</b>这些膜蛤粉红一般属于“尊蛤讨包”，他们看不惯习倒车，但他们坚定地拥护中共，比如认为六四的学生是“螳臂当车的暴徒”。翻翻老膜乎的帖子，有不少这样的例子。只要习还在倒行逆施，就会有更多人怀念相对自由的江湖时代，所以蛤丝群体粉红化必然会发生。江作为中共领导人必然作了很多恶，但跟习比起来却好得多，全靠同行衬托。所谓“两害相较取其轻”，如果实在没有其他选择，只能选择其中不那么烂的一个，但终究还是在比烂。<br />\r\n众所周知，江和薄本身有很多黑点：江在位时建墙，全国上下腐败盛行，下岗潮使大批工人失业，打压轮子血债累累，还与六四间接有关。虽说轮子不是什么好东西，但他们的战斗力比海外民运不知高到哪里去了，他们开发的翻墙软件夹带私货，却让很多大陆网民开始接触到墙外的世界。薄心狠手辣，如果他在权力斗争中击败习，现在会更接近毛时代，说不定早已闭关锁国成为下一个朝鲜。<br />\r\n所谓膜就是乳，就是模仿和重复领导人讲话，通过解构领袖升级大脑，不是为他们歌功颂德，更不是搞个人崇拜，去赞美他们的罪恶。老膜乎早就有人看穿了一切：<a href=\"https://www.mohu.rocks/question/648\" title=\"https://www.mohu.rocks/question/648\">如何评价真的在膜的人？</a><br />\r\n<b>请记住：我们反贼膜蛤(膜督)就是图一乐，学习他们的优点，但不能真的崇拜他们。</b>键政累了玩梗放松一下，真的在膜的人基本都是粉红。", "date": "2021-08-19", "agreeCount": 14, "discussionCount": 12}